idrac_ctl/__init__.py
idrac_ctl/__main__.py
idrac_ctl/cmd_boot.py
idrac_ctl/cmd_current_boot.py
idrac_ctl/cmd_exceptions.py
idrac_ctl/cmd_query.py
idrac_ctl/cmd_utils.py
idrac_ctl/idrac_main.py
idrac_ctl/idrac_manager.py
idrac_ctl/shared.py
idrac_ctl/version.py
idrac_ctl/attribute/__init__.py
idrac_ctl/attribute/cmd_attribute.py
idrac_ctl/attribute/cmd_attribute_clear_pending.py
idrac_ctl/bios/__init__.py
idrac_ctl/bios/bios_registry.py
idrac_ctl/bios/cmd_bios.py
idrac_ctl/bios/cmd_bios_clear_pending.py
idrac_ctl/bios/cmd_bios_pending.py
idrac_ctl/bios/cmd_bios_reset_default.py
idrac_ctl/bios/cmd_boot_order.py
idrac_ctl/bios/cmd_change_bios.py
idrac_ctl/boot_source/__init__.py
idrac_ctl/boot_source/cmd_boot_one_shot.py
idrac_ctl/boot_source/cmd_boot_options.py
idrac_ctl/boot_source/cmd_boot_settings.py
idrac_ctl/boot_source/cmd_boot_source_enable.py
idrac_ctl/boot_source/cmd_boot_source_get.py
idrac_ctl/boot_source/cmd_boot_sources_list.py
idrac_ctl/boot_source/cmd_clear_pending.py
idrac_ctl/chassis/__init__.py
idrac_ctl/chassis/cmd_chasis_reset.py
idrac_ctl/chassis/cmd_chassis_query.py
idrac_ctl/compute/__init__.py
idrac_ctl/compute/cmd_power_state.py
idrac_ctl/custom_argparser/__init__.py
idrac_ctl/custom_argparser/customer_argdefault.py
idrac_ctl/dell_lc/__init__.py
idrac_ctl/dell_lc/cmd_dell_lc_api.py
idrac_ctl/dell_lc/cmd_dell_lc_rs.py
idrac_ctl/dell_lc/cmd_dell_lc_services.py
idrac_ctl/delloem/__init__.py
idrac_ctl/delloem/delloem_actions.py
idrac_ctl/delloem/delloem_attach.py
idrac_ctl/delloem/delloem_attach_status.py
idrac_ctl/delloem/delloem_boot_netios.py
idrac_ctl/delloem/delloem_detach.py
idrac_ctl/delloem/delloem_disconnect.py
idrac_ctl/delloem/delloem_get_networkios.py
idrac_ctl/delloem/delloem_os_deployment.py
idrac_ctl/firmware/__init__.py
idrac_ctl/firmware/cmd_firmware.py
idrac_ctl/firmware/cmd_firmware_inv.py
idrac_ctl/jobs/__init__.py
idrac_ctl/jobs/cmd_job_apply.py
idrac_ctl/jobs/cmd_job_del.py
idrac_ctl/jobs/cmd_job_delete_all.py
idrac_ctl-1.0.13.dist-info/LICENSE
idrac_ctl-1.0.13.dist-info/METADATA
idrac_ctl-1.0.13.dist-info/WHEEL
idrac_ctl-1.0.13.dist-info/entry_points.txt
idrac_ctl-1.0.13.dist-info/top_level.txt
idrac_ctl-1.0.13.dist-info/RECORD
