Metadata-Version: 2.1
Name: idrac-ctl
Version: 1.0.13
Summary: Standalone command line tool to interact with Dell iDRAC via Redfish REST API.
Home-page: https://github.com/spyroot/idrac_ctl
Author: Mustafa Bayramov
Author-email: spyroot@gmail.com
License: MIT
Requires-Python: >=3.10
License-File: LICENSE
Requires-Dist: requests (~=2.28.2)
Requires-Dist: tqdm (~=4.61)
Requires-Dist: urllib3 (~=1.26.6)
Requires-Dist: pygments (==2.14.0)
Requires-Dist: setuptools (~=67.0.0)
Provides-Extra: dev
Requires-Dist: pytest (>=3.7) ; extra == 'dev'
